{
  "$schema": "tab_schema.json",
  "data": {
    "selectedColor": "#26a38c",
    "unselectedColor": "#999999",
    "tabs": [
      {
        "index": "0",
        "title": "首页",
        "image": "./imgs/launcher/cyanBlue/home_nor@3x.png",
        "selectedImage": "./imgs/launcher/cyanBlue/home_sel3.png",
        "src": "index.weex.js?Page=Tab_home",
        "visibility": "visible"
      },
      {
        "index": "1",
        "title": "工作台",
        "image": "./imgs/launcher/cyanBlue/work_nor@3x.png",
        "selectedImage": "./imgs/launcher/cyanBlue/work_sel3.png",
        "src": "index.weex.js?Page=Tab_bench",
        "visibility": "hidden"
      },
      {
        "index": "2",
        "title": "我的",
        "image": "./imgs/launcher/cyanBlue/user_nor@3x.png",
        "selectedImage": "./imgs/launcher/cyanBlue/user_sel3.png",
        "src": "index.weex.js?Page=Tab_user",
        "visibility": "hidden"
      } 
    ]
  }
}
